Workbook

Sheet Summary
A1: Mapping the Shrines of Pakistan: costed expansion, December 2026 to December 2027
A2: Prepared by Rauf Nawaz for discussion with Professor Teren Sevea, 13 October 2026. Estimates, not quotations; every figure traces to the Assumptions sheet.
A4: Exchange rate (PKR per USD) | B4: =Assumptions!$C$5 -> 277
A6: Category | B6: Tier 1 adds (USD) | C6: Tier 2 adds (USD) | D6: Tier 3 adds (USD) | E6: Tier 1 total (USD) | F6: Tier 2 cumulative (USD) | G6: Tier 3 cumulative (USD) | H6: Tier 3 cumulative (PKR)
A7: Fieldwork teams and travel | B7: =SUMIFS('Line Items'!$G$5:$G$210,'Line Items'!$A$5:$A$210,1,'Line Items'!$B$5:$B$210,$A7) -> 1792.491 | C7: =SUMIFS('Line Items'!$G$5:$G$210,'Line Items'!$A$5:$A$210,2,'Line Items'!$B$5:$B$210,$A7) -> 5519.8195 | D7: =SUMIFS('Line Items'!$G$5:$G$210,'Line Items'!$A$5:$A$210,3,'Line Items'!$B$5:$B$210,$A7) -> 3810.0397 | E7: =B7 -> 1792.491 | F7: =B7+C7 -> 7312.3105 | G7: =B7+C7+D7 -> 11122.35 | H7: =G7*$B$4 -> 3080891
A8: Interviews | B8: =SUMIFS('Line Items'!$G$5:$G$210,'Line Items'!$A$5:$A$210,1,'Line Items'!$B$5:$B$210,$A8) -> 1121.9458 | C8: =SUMIFS('Line Items'!$G$5:$G$210,'Line Items'!$A$5:$A$210,2,'Line Items'!$B$5:$B$210,$A8) -> 997.2852 | D8: =SUMIFS('Line Items'!$G$5:$G$210,'Line Items'!$A$5:$A$210,3,'Line Items'!$B$5:$B$210,$A8) -> 685.63357 | E8: =B8 -> 1121.9458 | F8: =B8+C8 -> 2119.231 | G8: =B8+C8+D8 -> 2804.8646 | H8: =G8*$B$4 -> 776947.5
A9: Data and coding | B9: =SUMIFS('Line Items'!$G$5:$G$210,'Line Items'!$A$5:$A$210,1,'Line Items'!$B$5:$B$210,$A9) -> 270 | C9: =SUMIFS('Line Items'!$G$5:$G$210,'Line Items'!$A$5:$A$210,2,'Line Items'!$B$5:$B$210,$A9) -> 240 | D9: =SUMIFS('Line Items'!$G$5:$G$210,'Line Items'!$A$5:$A$210,3,'Line Items'!$B$5:$B$210,$A9) -> 165 | E9: =B9 -> 270 | F9: =B9+C9 -> 510 | G9: =B9+C9+D9 -> 675 | H9: =G9*$B$4 -> 186975
A10: Principal investigator travel | B10: =SUMIFS('Line Items'!$G$5:$G$210,'Line Items'!$A$5:$A$210,1,'Line Items'!$B$5:$B$210,$A10) -> 1450 | C10: =SUMIFS('Line Items'!$G$5:$G$210,'Line Items'!$A$5:$A$210,2,'Line Items'!$B$5:$B$210,$A10) -> 2147.5 | D10: =SUMIFS('Line Items'!$G$5:$G$210,'Line Items'!$A$5:$A$210,3,'Line Items'!$B$5:$B$210,$A10) -> 765 | E10: =B10 -> 1450 | F10: =B10+C10 -> 3597.5 | G10: =B10+C10+D10 -> 4362.5 | H10: =G10*$B$4 -> 1208412.5
A11: Urs and qawwali recording | B11: =SUMIFS('Line Items'!$G$5:$G$210,'Line Items'!$A$5:$A$210,1,'Line Items'!$B$5:$B$210,$A11) -> 726.30325 | C11: =SUMIFS('Line Items'!$G$5:$G$210,'Line Items'!$A$5:$A$210,2,'Line Items'!$B$5:$B$210,$A11) -> 968.40433 | D11: =SUMIFS('Line Items'!$G$5:$G$210,'Line Items'!$A$5:$A$210,3,'Line Items'!$B$5:$B$210,$A11) -> 726.30325 | E11: =B11 -> 726.30325 | F11: =B11+C11 -> 1694.7076 | G11: =B11+C11+D11 -> 2421.0108 | H11: =G11*$B$4 -> 670620
A12: Oral histories | B12: =SUMIFS('Line Items'!$G$5:$G$210,'Line Items'!$A$5:$A$210,1,'Line Items'!$B$5:$B$210,$A12) -> 180 | C12: =SUMIFS('Line Items'!$G$5:$G$210,'Line Items'!$A$5:$A$210,2,'Line Items'!$B$5:$B$210,$A12) -> 180 | D12: =SUMIFS('Line Items'!$G$5:$G$210,'Line Items'!$A$5:$A$210,3,'Line Items'!$B$5:$B$210,$A12) -> 144 | E12: =B12 -> 180 | F12: =B12+C12 -> 360 | G12: =B12+C12+D12 -> 504 | H12: =G12*$B$4 -> 139608
A13: Digitisation of books | B13: =SUMIFS('Line Items'!$G$5:$G$210,'Line Items'!$A$5:$A$210,1,'Line Items'!$B$5:$B$210,$A13) -> 508.5 | C13: =SUMIFS('Line Items'!$G$5:$G$210,'Line Items'!$A$5:$A$210,2,'Line Items'!$B$5:$B$210,$A13) -> 1017 | D13: =SUMIFS('Line Items'!$G$5:$G$210,'Line Items'!$A$5:$A$210,3,'Line Items'!$B$5:$B$210,$A13) -> 1017 | E13: =B13 -> 508.5 | F13: =B13+C13 -> 1525.5 | G13: =B13+C13+D13 -> 2542.5 | H13: =G13*$B$4 -> 704272.5
A14: Equipment | B14: =SUMIFS('Line Items'!$G$5:$G$210,'Line Items'!$A$5:$A$210,1,'Line Items'!$B$5:$B$210,$A14) -> 1363.4296 | C14: =SUMIFS('Line Items'!$G$5:$G$210,'Line Items'!$A$5:$A$210,2,'Line Items'!$B$5:$B$210,$A14) -> 490 | D14: =SUMIFS('Line Items'!$G$5:$G$210,'Line Items'!$A$5:$A$210,3,'Line Items'!$B$5:$B$210,$A14) -> 1100 | E14: =B14 -> 1363.4296 | F14: =B14+C14 -> 1853.4296 | G14: =B14+C14+D14 -> 2953.4296 | H14: =G14*$B$4 -> 818100
A15: Running costs | B15: =SUMIFS('Line Items'!$G$5:$G$210,'Line Items'!$A$5:$A$210,1,'Line Items'!$B$5:$B$210,$A15) -> 170 | C15: =SUMIFS('Line Items'!$G$5:$G$210,'Line Items'!$A$5:$A$210,2,'Line Items'!$B$5:$B$210,$A15) -> 200 | D15: =SUMIFS('Line Items'!$G$5:$G$210,'Line Items'!$A$5:$A$210,3,'Line Items'!$B$5:$B$210,$A15) -> 320 | E15: =B15 -> 170 | F15: =B15+C15 -> 370 | G15: =B15+C15+D15 -> 690 | H15: =G15*$B$4 -> 191130
A16: Dissemination | B16: =SUMIFS('Line Items'!$G$5:$G$210,'Line Items'!$A$5:$A$210,1,'Line Items'!$B$5:$B$210,$A16) -> 0 | C16: =SUMIFS('Line Items'!$G$5:$G$210,'Line Items'!$A$5:$A$210,2,'Line Items'!$B$5:$B$210,$A16) -> 250 | D16: =SUMIFS('Line Items'!$G$5:$G$210,'Line Items'!$A$5:$A$210,3,'Line Items'!$B$5:$B$210,$A16) -> 250 | E16: =B16 -> 0 | F16: =B16+C16 -> 250 | G16: =B16+C16+D16 -> 500 | H16: =G16*$B$4 -> 138500
A17: Subtotal | B17: =SUM(B7:B16) -> 7582.6697 | C17: =SUM(C7:C16) -> 12010.009 | D17: =SUM(D7:D16) -> 8982.9765 | E17: =SUM(E7:E16) -> 7582.6697 | F17: =SUM(F7:F16) -> 19592.679 | G17: =SUM(G7:G16) -> 28575.655 | H17: =SUM(H7:H16) -> 7915456.5
A18: Contingency | B18: =B17*Assumptions!$C$6 -> 758.26697 | C18: =C17*Assumptions!$C$6 -> 1201.0009 | D18: =D17*Assumptions!$C$6 -> 898.29765 | E18: =E17*Assumptions!$C$6 -> 758.26697 | F18: =F17*Assumptions!$C$6 -> 1959.2679 | G18: =G17*Assumptions!$C$6 -> 2857.5655 | H18: =H17*Assumptions!$C$6 -> 791545.65
A19: Total | B19: =B17+B18 -> 8340.9366 | C19: =C17+C18 -> 13211.01 | D19: =D17+D18 -> 9881.2742 | E19: =E17+E18 -> 8340.9366 | F19: =F17+F18 -> 21551.947 | G19: =G17+G18 -> 31433.221 | H19: =H17+H18 -> 8707002.2
A21: Scale and unit cost
A22: Shrines coded (cumulative) | E22: =SUMIFS(Regions!$C$5:$C$17,Regions!$A$5:$A$17,"<="&1) -> 36 | F22: =SUMIFS(Regions!$C$5:$C$17,Regions!$A$5:$A$17,"<="&2) -> 68 | G22: =SUMIFS(Regions!$C$5:$C$17,Regions!$A$5:$A$17,"<="&3) -> 90
A23: Total cost per shrine coded (all costs) | E23: =E19/E22 -> 231.69268 | F23: =F19/F22 -> 316.94039 | G23: =G19/G22 -> 349.25801
A24: Books digitised (cumulative) | E24: =SUMIFS('Line Items'!$D$5:$D$210,'Line Items'!$A$5:$A$210,"<="&1,'Line Items'!$C$5:$C$210,"Books digitised*") -> 30 | F24: =SUMIFS('Line Items'!$D$5:$D$210,'Line Items'!$A$5:$A$210,"<="&2,'Line Items'!$C$5:$C$210,"Books digitised*") -> 90 | G24: =SUMIFS('Line Items'!$D$5:$D$210,'Line Items'!$A$5:$A$210,"<="&3,'Line Items'!$C$5:$C$210,"Books digitised*") -> 150
A25: Urs and qawwali events recorded (cumulative) | E25: =SUMIFS('Line Items'!$D$5:$D$210,'Line Items'!$A$5:$A$210,"<="&1,'Line Items'!$C$5:$C$210,"Events recorded*") -> 3 | F25: =SUMIFS('Line Items'!$D$5:$D$210,'Line Items'!$A$5:$A$210,"<="&2,'Line Items'!$C$5:$C$210,"Events recorded*") -> 7 | G25: =SUMIFS('Line Items'!$D$5:$D$210,'Line Items'!$A$5:$A$210,"<="&3,'Line Items'!$C$5:$C$210,"Events recorded*") -> 10
A26: Interviews (cumulative) | E26: =E22*Assumptions!$C$13 -> 180 | F26: =F22*Assumptions!$C$13 -> 340 | G26: =G22*Assumptions!$C$13 -> 450
A28: Funding already requested
A29: Mittal Institute Winter Session Grant (pending, due 15 October 2026) | E29: 2950
A30: Tier 1 balance still to raise | E30: =E19-E29 -> 5390.9366
A31: Tiers 2 and 3 to raise | F31: =C19 -> 13211.01 | G31: =D19 -> 9881.2742
A33: Tier 1, Lahore and Pakpattan core: the 36 shrine winter sample in the Mittal proposal, carried through the year with oral histories, three urs recordings and the first 30 books digitised.
A34: Tier 2, Punjab expansion (summer 2027): Multan, Uch Sharif and Bahawalpur, Jhang, Okara, Kasur, Taunsa and Dera Ghazi Khan; two teams in parallel; 60 more books.
A35: Tier 3, beyond Punjab (autumn 2027): Karachi, Thatta, Sehwan, Hyderabad and Bhit Shah in Sindh, Islamabad and Rawalpindi, and Peshawar, with locally hired Sindhi and Pashto speaking enumerators.
A36: Excluded: Balochistan, for reasons of security and access; Rauf's own time, which is unpaid; lodging in Lahore, which family provides.
A37: Colour code: blue text is an input, green text links to another sheet, black text is a formula. Yellow rows on the Assumptions sheet are judgement calls to confirm.

Sheet Assumptions
A1: Assumptions and unit costs
A2: Blue cells are inputs: change them and every sheet recalculates. Yellow rows are judgement calls Rauf should confirm before the budget goes to a funder.
A4: Key | B4: Assumption | C4: Value | D4: Unit | E4: Basis and source
A5: fx | B5: Exchange rate | C5: 277 | D5: PKR per USD | E5: Rupee closed at 277.11 per USD on 30 September 2026 (ProPakistani). Revisit at submission.
A6: contingency | B6: Contingency | C6: 0.1 | D6: share of subtotal | E6: Standard allowance for fare and price movement; the rupee and fuel linked bus fares both move.
A7: enum_day | B7: Enumerator day rate | C7: 15 | D7: USD per day | E7: The project's own rate in the Mittal budget ($450 for 30 enumerator days), about PKR 4,150 a day. Punjab minimum wage is PKR 40,000 a month from 1 July 2025 (WageIndicator), about PKR 1,540 a working day, so the rate is roughly 2.7 times the minimum.
A8: coord_day | B8: Field coordinator day rate | C8: 25 | D8: USD per day | E8: Assumption: a senior enumerator who supervises outstation teams, checks forms daily and manages consent records.
A9: fem_day | B9: Female enumerator day rate | C9: 15 | D9: USD per day | E9: Same rate as other enumerators, so that the women's strand is not paid less.
A10: visits_per_shrine | B10: Observation visits per shrine | C10: 2 | D10: visits | E10: Proposal design: one weekday visit and one Thursday evening visit.
A11: visits_per_day | B11: Visits completed per team day | C11: 2.4 | D11: visits | E11: Mittal budget basis: 72 visits in 30 enumerator days.
A12: fem_days_per_shrine | B12: Female enumerator days per shrine | C12: 0.5 | D12: days | E12: Assumption: women's spaces and women devotee interviews take about half a day per shrine.
A13: interviews_per_shrine | B13: Interviews per shrine | C13: 5 | D13: interviews | E13: Proposal design: custodian or Auqaf manager, senior khadim, three devotees.
A14: devotees_per_shrine | B14: Devotee interviews per shrine | C14: 3 | D14: interviews | E14: Proposal design.
A15: interview_min | B15: Average interview length | C15: 25 | D15: minutes | E15: Assumption for a semi structured interview in Urdu or Punjabi.
A16: token_pkr | B16: Token of thanks per devotee interview | C16: 500 | D16: PKR | E16: Assumption: a small gift in kind or cash. Whether to offer one at all is an ethics question for CUHS and Rauf.
... A49: sindhi_review_days | B49: Sindhi and Pashto translation review days | C49: 10 | D49: days | E49: Assumption: a reviewer checks instrument translations and transcripts for Tier 3.

Sheet Regions
A1: Fieldwork regions by tier
A2: Shrine counts, fares and team composition are inputs (blue). Field days, nights and visits are computed.
A4: Tier | B4: Region | C4: Shrines | D4: Travelling team (people) | E4: Round trip fare per traveller (PKR) | F4: Domestic flights per traveller (one way legs) | G4: Hired car days | H4: Local hires (enumerators) | I4: Visits | J4: Team field days | K4: Enumerator days | L4: Female enumerator days | M4: Coordinator days | N4: Nights away | O4: Example shrines | P4: Notes
A5: 1 | B5: Lahore | C5: 30 | D5: 0 | E5: 0 | F5: 0 | G5: 0 | H5: 0 | I5: =C5*Assumptions!$C$10 -> 60 | J5: =ROUNDUP(I5/Assumptions!$C$11,0) -> 25 | K5: =IF(D5=0,J5,J5*2) -> 25 | L5: =C5*Assumptions!$C$12 -> 15 | M5: =IF(D5=0,0,J5) -> 0 | N5: =IF(OR(D5=0,B5="Kasur"),0,J5+1) -> 0 | O5: Data Darbar, Bibi Pak Daman, Madho Lal Hussain, Shah Jamal, Abul Muali Qadri, Wasif Ali Wasif | P5: Home city; lodging with family; Mittal winter sample.
A6: 1 | B6: Pakpattan | C6: 6 | D6: 3 | E6: 3000 | F6: 0 | G6: 0 | H6: 0 | I6: =C6*Assumptions!$C$10 -> 12 | J6: =ROUNDUP(I6/Assumptions!$C$11,0) -> 5 | K6: =IF(D6=0,J6,J6*2) -> 10 | L6: =C6*Assumptions!$C$12 -> 3 | M6: =IF(D6=0,0,J6) -> 5 | N6: =IF(OR(D6=0,B6="Kasur"),0,J6+1) -> 6 | O6: Baba Farid Ganj Shakar and five district shrines | P6: Mittal winter sample. No listed Daewoo fare; PKR 1,500 each way assumed via Okara (Okara fare PKR 890).
A7: 2 | B7: Multan | C7: 8 | D7: 3 | E7: 6860 | F7: 0 | G7: 0 | H7: 0 | I7: =C7*Assumptions!$C$10 -> 16 | J7: =ROUNDUP(I7/Assumptions!$C$11,0) -> 7 | K7: =IF(D7=0,J7,J7*2) -> 14 | L7: =C7*Assumptions!$C$12 -> 4 | M7: =IF(D7=0,0,J7) -> 7 | N7: =IF(OR(D7=0,B7="Kasur"),0,J7+1) -> 8 | O7: Bahauddin Zakariya, Shah Rukn e Alam, Shams Tabrez | P7: Daewoo Gold Lahore to Multan PKR 3,430 each way.
A8: 2 | B8: Uch Sharif and Bahawalpur | C8: 8 | D8: 3 | E8: 6160 | F8: 0 | G8: 0 | H8: 0 | I8: =C8*Assumptions!$C$10 -> 16 | J8: =ROUNDUP(I8/Assumptions!$C$11,0) -> 7 | K8: =IF(D8=0,J8,J8*2) -> 14 | L8: =C8*Assumptions!$C$12 -> 4 | M8: =IF(D8=0,0,J8) -> 7 | N8: =IF(OR(D8=0,B8="Kasur"),0,J8+1) -> 8 | O8: Jalaluddin Surkh Bukhari, Bibi Jawindi, Gilani shrines of Uch | P8: Daewoo Gold Lahore to Bahawalpur PKR 2,580 each way plus PKR 500 each way to Uch (assumed).
A9: 2 | B9: Jhang | C9: 4 | D9: 3 | E9: 3160 | F9: 0 | G9: 0 | H9: 0 | I9: =C9*Assumptions!$C$10 -> 8 | J9: =ROUNDUP(I9/Assumptions!$C$11,0) -> 4 | K9: =IF(D9=0,J9,J9*2) -> 8 | L9: =C9*Assumptions!$C$12 -> 2 | M9: =IF(D9=0,0,J9) -> 4 | N9: =IF(OR(D9=0,B9="Kasur"),0,J9+1) -> 5 | O9: Shrines of Jhang and Shorkot, including Sultan Bahu at Garh Maharaja | P9: Daewoo Lahore to Jhang PKR 1,580 each way. Rehman and Lund Thomsen's lodge is in Jhang.
A10: 2 | B10: Okara | C10: 4 | D10: 3 | E10: 1780 | F10: 0 | G10: 0 | H10: 0 | I10: =C10*Assumptions!$C$10 -> 8 | J10: =ROUNDUP(I10/Assumptions!$C$11,0) -> 4 | K10: =IF(D10=0,J10,J10*2) -> 8 | L10: =C10*Assumptions!$C$12 -> 2 | M10: =IF(D10=0,0,J10) -> 4 | N10: =IF(OR(D10=0,B10="Kasur"),0,J10+1) -> 5 | O10: District shrines of Okara and Dipalpur | P10: Daewoo Lahore to Okara PKR 890 each way.
A11: 2 | B11: Kasur | C11: 4 | D11: 2 | E11: 1200 | F11: 0 | G11: 0 | H11: 0 | I11: =C11*Assumptions!$C$10 -> 8 | J11: =ROUNDUP(I11/Assumptions!$C$11,0) -> 4 | K11: =IF(D11=0,J11,J11*2) -> 8 | L11: =C11*Assumptions!$C$12 -> 2 | M11: =IF(D11=0,0,J11) -> 4 | N11: =IF(OR(D11=0,B11="Kasur"),0,J11+1) -> 0 | O11: Bulleh Shah and district shrines | P11: Day trips from Lahore; no lodging; PKR 600 each way assumed.
A12: 2 | B12: Taunsa and Dera Ghazi Khan | C12: 4 | D12: 3 | E12: 8000 | F12: 0 | G12: 0 | H12: 0 | I12: =C12*Assumptions!$C$10 -> 8 | J12: =ROUNDUP(I12/Assumptions!$C$11,0) -> 4 | K12: =IF(D12=0,J12,J12*2) -> 8 | L12: =C12*Assumptions!$C$12 -> 2 | M12: =IF(D12=0,0,J12) -> 4 | N12: =IF(OR(D12=0,B12="Kasur"),0,J12+1) -> 5 | O12: Taunsa Sharif, Sakhi Sarwar | P12: Lahore to Multan PKR 3,430 plus Multan to Dera Ghazi Khan PKR 570, each way.
A13: 3 | B13: Sindh: Karachi and Thatta | C13: 6 | D13: 1 | E13: 0 | F13: 2 | G13: 4 | H13: 2 | I13: =C13*Assumptions!$C$10 -> 12 | J13: =ROUNDUP(I13/Assumptions!$C$11,0) -> 5 | K13: =IF(D13=0,J13,J13*2) -> 10 | L13: =C13*Assumptions!$C$12 -> 3 | M13: =IF(D13=0,0,J13) -> 5 | N13: =IF(OR(D13=0,B13="Kasur"),0,J13+1) -> 6 | O13: Abdullah Shah Ghazi, Makli necropolis shrines | P13: Coordinator flies from Lahore; Sindhi speaking enumerators hired locally.
A14: 3 | B14: Sindh: Sehwan | C14: 4 | D14: 1 | E14: 0 | F14: 0 | G14: 3 | H14: 2 | I14: =C14*Assumptions!$C$10 -> 8 | J14: =ROUNDUP(I14/Assumptions!$C$11,0) -> 4 | K14: =IF(D14=0,J14,J14*2) -> 8 | L14: =C14*Assumptions!$C$12 -> 2 | M14: =IF(D14=0,0,J14) -> 4 | N14: =IF(OR(D14=0,B14="Kasur"),0,J14+1) -> 5 | O14: Lal Shahbaz Qalandar and Sehwan shrines | P14: By hired car from Karachi or Hyderabad. Local hires.
A15: 3 | B15: Sindh: Hyderabad and Bhit Shah | C15: 4 | D15: 1 | E15: 0 | F15: 0 | G15: 3 | H15: 2 | I15: =C15*Assumptions!$C$10 -> 8 | J15: =ROUNDUP(I15/Assumptions!$C$11,0) -> 4 | K15: =IF(D15=0,J15,J15*2) -> 8 | L15: =C15*Assumptions!$C$12 -> 2 | M15: =IF(D15=0,0,J15) -> 4 | N15: =IF(OR(D15=0,B15="Kasur"),0,J15+1) -> 5 | O15: Shah Abdul Latif Bhittai, Hyderabad shrines | P15: By hired car. Local hires.
A16: 3 | B16: Islamabad and Rawalpindi | C16: 4 | D16: 3 | E16: 5960 | F16: 0 | G16: 0 | H16: 0 | I16: =C16*Assumptions!$C$10 -> 8 | J16: =ROUNDUP(I16/Assumptions!$C$11,0) -> 4 | K16: =IF(D16=0,J16,J16*2) -> 8 | L16: =C16*Assumptions!$C$12 -> 2 | M16: =IF(D16=0,0,J16) -> 4 | N16: =IF(OR(D16=0,B16="Kasur"),0,J16+1) -> 5 | O16: Bari Imam, Golra Sharif | P16: Daewoo Gold Lahore to Islamabad PKR 2,980 each way.
A17: 3 | B17: Peshawar | C17: 4 | D17: 1 | E17: 9000 | F17: 0 | G17: 0 | H17: 2 | I17: =C17*Assumptions!$C$10 -> 8 | J17: =ROUNDUP(I17/Assumptions!$C$11,0) -> 4 | K17: =IF(D17=0,J17,J17*2) -> 8 | L17: =C17*Assumptions!$C$12 -> 2 | M17: =IF(D17=0,0,J17) -> 4 | N17: =IF(OR(D17=0,B17="Kasur"),0,J17+1) -> 5 | O17: Rahman Baba and Peshawar shrines | P17: Coordinator travels; Pashto speaking enumerators hired locally. PKR 4,500 each way assumed.
B18: Total | C18: =SUM(C5:C17) -> 90
A20: Note: Kasur is costed as day trips, so it carries fares but no nights away. In Sindh and Peshawar only the coordinator travels; enumerators are hired locally so that interviews run in Sindhi and Pashto.

Sheet Line Items
A1: Line items
A2: Each tier lists only what it adds. Tiers are cumulative on the Summary sheet. Quantities and unit costs are formulas that point to the Assumptions and Regions sheets.
A4: Tier | B4: Category | C4: Item | D4: Quantity | E4: Unit | F4: Unit cost (USD) | G4: Total (USD) | H4: Total (PKR) | I4: Basis
A5: 1 | B5: Fieldwork teams and travel | C5: Lahore: enumerator days | D5: =Regions!K5 -> 25 | E5: enumerator days | F5: =Assumptions!$C$7 -> 15 | G5: =D5*F5 -> 375 | H5: =G5*Assumptions!$C$5 -> 103875 | I5: Two enumerators per visit outside Lahore; singly in Lahore, as in the Mittal budget.
A6: 1 | B6: Fieldwork teams and travel | C6: Lahore: female enumerator days | D6: =Regions!L5 -> 15 | E6: days | F6: =Assumptions!$C$9 -> 15 | G6: =D6*F6 -> 225 | H6: =G6*Assumptions!$C$5 -> 62325 | I6: Women's spaces and women devotee interviews.
A7: 1 | B7: Fieldwork teams and travel | C7: Lahore: field coordinator days | D7: =Regions!M5 -> 0 | E7: days | F7: =Assumptions!$C$8 -> 25 | G7: =D7*F7 -> 0 | H7: =G7*Assumptions!$C$5 -> 0 | I7: Supervision of outstation teams.
A8: 1 | B8: Fieldwork teams and travel | C8: Lahore: local transport | D8: =Regions!J5 -> 25 | E8: team field days | F8: =Assumptions!$C$22 -> 8 | G8: =D8*F8 -> 200 | H8: =G8*Assumptions!$C$5 -> 55400 | I8: Ride hail and rickshaw between sites.
A9: 1 | B9: Fieldwork teams and travel | C9: Lahore: lodging | D9: =ROUNDUP(Regions!D5/Assumptions!$C$20,0)*Regions!N5 -> 0 | E9: room nights | F9: =Assumptions!$C$19 -> 35 | G9: =D9*F9 -> 0 | H9: =G9*Assumptions!$C$5 -> 0 | I9: Budget hotel, twin share.
A10: 1 | B10: Fieldwork teams and travel | C10: Lahore: meals away from home | D10: =Regions!D5*Regions!N5 -> 0 | E10: traveller days | F10: =Assumptions!$C$21 -> 10 | G10: =D10*F10 -> 0 | H10: =G10*Assumptions!$C$5 -> 0 | I10: Per traveller per night away.
A11: 1 | B11: Interviews | C11: Lahore: transcription and translation | D11: =Regions!C5*Assumptions!$C$13*Assumptions!$C$15/60 -> 62.5 | E11: audio hours | F11: =Assumptions!$C$17 -> 12 | G11: =D11*F11 -> 750 | H11: =G11*Assumptions!$C$5 -> 207750 | I11: Five interviews per shrine.
A12: 1 | B12: Interviews | C12: Lahore: tokens of thanks to devotees | D12: =Regions!C5*Assumptions!$C$14 -> 90 | E12: interviews | F12: =Assumptions!$C$16/Assumptions!$C$5 -> 1.8050542 | G12: =D12*F12 -> 162.45487 | H12: =G12*Assumptions!$C$5 -> 45000 | I12: Subject to CUHS and Rauf's decision.
A13: 1 | B13: Interviews | C13: Lahore: consent forms and printing | D13: =Regions!C5*Assumptions!$C$13 -> 150 | E13: interviews | F13: =Assumptions!$C$28 -> 0.15 | G13: =D13*F13 -> 22.5 | H13: =G13*Assumptions!$C$5 -> 6232.5
A14: 1 | B14: Data and coding | C14: Lahore: data entry and coding | D14: =Regions!C5*Assumptions!$C$18 -> 15 | E14: days | F14: =Assumptions!$C$7 -> 15 | G14: =D14*F14 -> 225 | H14: =G14*Assumptions!$C$5 -> 62325 | I14: Function module entry and double check.
A15: 1 | B15: Fieldwork teams and travel | C15: Pakpattan: enumerator days | D15: =Regions!K6 -> 10 | E15: enumerator days | F15: =Assumptions!$C$7 -> 15 | G15: =D15*F15 -> 150 | H15: =G15*Assumptions!$C$5 -> 41550 | I15: Two enumerators per visit outside Lahore; singly in Lahore, as in the Mittal budget.
A16: 1 | B16: Fieldwork teams and travel | C16: Pakpattan: female enumerator days | D16: =Regions!L6 -> 3 | E16: days | F16: =Assumptions!$C$9 -> 15 | G16: =D16*F16 -> 45 | H16: =G16*Assumptions!$C$5 -> 12465 | I16: Women's spaces and women devotee interviews.
A17: 1 | B17: Fieldwork teams and travel | C17: Pakpattan: field coordinator days | D17: =Regions!M6 -> 5 | E17: days | F17: =Assumptions!$C$8 -> 25 | G17: =D17*F17 -> 125 | H17: =G17*Assumptions!$C$5 -> 34625 | I17: Supervision of outstation teams.
A18: 1 | B18: Fieldwork teams and travel | C18: Pakpattan: local transport | D18: =Regions!J6 -> 5 | E18: team field days | F18: =Assumptions!$C$22 -> 8 | G18: =D18*F18 -> 40 | H18: =G18*Assumptions!$C$5 -> 11080 | I18: Ride hail and rickshaw between sites.
A19: 1 | B19: Fieldwork teams and travel | C19: Pakpattan: intercity fares | D19: =Regions!D6 -> 3 | E19: travellers | F19: =Regions!E6/Assumptions!$C$5 -> 10.830325 | G19: =D19*F19 -> 32.490975 | H19: =G19*Assumptions!$C$5 -> 9000 | I19: Round trip bus fare per traveller; see Regions.
A20: 1 | B20: Fieldwork teams and travel | C20: Pakpattan: lodging | D20: =ROUNDUP(Regions!D6/Assumptions!$C$20,0)*Regions!N6 -> 12 | E20: room nights | F20: =Assumptions!$C$19 -> 35 | G20: =D20*F20 -> 420 | H20: =G20*Assumptions!$C$5 -> 116340 | I20: Budget hotel, twin share.
A21: 1 | B21: Fieldwork teams and travel | C21: Pakpattan: meals away from home | D21: =Regions!D6*Regions!N6 -> 18 | E21: traveller days | F21: =Assumptions!$C$21 -> 10 | G21: =D21*F21 -> 180 | H21: =G21*Assumptions!$C$5 -> 49860 | I21: Per traveller per night away.
A22: 1 | B22: Interviews | C22: Pakpattan: transcription and translation | D22: =Regions!C6*Assumptions!$C$13*Assumptions!$C$15/60 -> 12.5 | E22: audio hours | F22: =Assumptions!$C$17 -> 12 | G22: =D22*F22 -> 150 | H22: =G22*Assumptions!$C$5 -> 41550 | I22: Five interviews per shrine.
A23: 1 | B23: Interviews | C23: Pakpattan: tokens of thanks to devotees | D23: =Regions!C6*Assumptions!$C$14 -> 18 | E23: interviews | F23: =Assumptions!$C$16/Assumptions!$C$5 -> 1.8050542 | G23: =D23*F23 -> 32.490975 | H23: =G23*Assumptions!$C$5 -> 9000 | I23: Subject to CUHS and Rauf's decision.
A24: 1 | B24: Interviews | C24: Pakpattan: consent forms and printing | D24: =Regions!C6*Assumptions!$C$13 -> 30 | E24: interviews | F24: =Assumptions!$C$28 -> 0.15 | G24: =D24*F24 -> 4.5 | H24: =G24*Assumptions!$C$5 -> 1246.5
A25: 1 | B25: Data and coding | C25: Pakpattan: data entry and coding | D25: =Regions!C6*Assumptions!$C$18 -> 3 | E25: days | F25: =Assumptions!$C$7 -> 15 | G25: =D25*F25 -> 45 | H25: =G25*Assumptions!$C$5 -> 12465 | I25: Function module entry and double check.
A26: 2 | B26: Fieldwork teams and travel | C26: Multan: enumerator days | D26: =Regions!K7 -> 14 | E26: enumerator days | F26: =Assumptions!$C$7 -> 15 | G26: =D26*F26 -> 210 | H26: =G26*Assumptions!$C$5 -> 58170 | I26: Two enumerators per visit outside Lahore; singly in Lahore, as in the Mittal budget.
A27: 2 | B27: Fieldwork teams and travel | C27: Multan: female enumerator days | D27: =Regions!L7 -> 4 | E27: days | F27: =Assumptions!$C$9 -> 15 | G27: =D27*F27 -> 60 | H27: =G27*Assumptions!$C$5 -> 16620 | I27: Women's spaces and women devotee interviews.
A28: 2 | B28: Fieldwork teams and travel | C28: Multan: field coordinator days | D28: =Regions!M7 -> 7 | E28: days | F28: =Assumptions!$C$8 -> 25 | G28: =D28*F28 -> 175 | H28: =G28*Assumptions!$C$5 -> 48475 | I28: Supervision of outstation teams.
A29: 2 | B29: Fieldwork teams and travel | C29: Multan: local transport | D29: =Regions!J7 -> 7 | E29: team field days | F29: =Assumptions!$C$22 -> 8 | G29: =D29*F29 -> 56 | H29: =G29*Assumptions!$C$5 -> 15512 | I29: Ride hail and rickshaw between sites.
A30: 2 | B30: Fieldwork teams and travel | C30: Multan: intercity fares | D30: =Regions!D7 -> 3 | E30: travellers | F30: =Regions!E7/Assumptions!$C$5 -> 24.765343 | G30: =D30*F30 -> 74.296029 | H30: =G30*Assumptions!$C$5 -> 20580 | I30: Round trip bus fare per traveller; see Regions.
A31: 2 | B31: Fieldwork teams and travel | C31: Multan: lodging | D31: =ROUNDUP(Regions!D7/Assumptions!$C$20,0)*Regions!N7 -> 16 | E31: room nights | F31: =Assumptions!$C$19 -> 35 | G31: =D31*F31 -> 560 | H31: =G31*Assumptions!$C$5 -> 155120 | I31: Budget hotel, twin share.
A32: 2 | B32: Fieldwork teams and travel | C32: Multan: meals away from home | D32: =Regions!D7*Regions!N7 -> 24 | E32: traveller days | F32: =Assumptions!$C$21 -> 10 | G32: =D32*F32 -> 240 | H32: =G32*Assumptions!$C$5 -> 66480 | I32: Per traveller per night away.
A33: 2 | B33: Interviews | C33: Multan: transcription and translation | D33: =Regions!C7*Assumptions!$C$13*Assumptions!$C$15/60 -> 16.666667 | E33: audio hours | F33: =Assumptions!$C$17 -> 12 | G33: =D33*F33 -> 200 | H33: =G33*Assumptions!$C$5 -> 55400 | I33: Five interviews per shrine.
A34: 2 | B34: Interviews | C34: Multan: tokens of thanks to devotees | D34: =Regions!C7*Assumptions!$C$14 -> 24 | E34: interviews | F34: =Assumptions!$C$16/Assumptions!$C$5 -> 1.8050542 | G34: =D34*F34 -> 43.3213 | H34: =G34*Assumptions!$C$5 -> 12000 | I34: Subject to CUHS and Rauf's decision.
A35: 2 | B35: Interviews | C35: Multan: consent forms and printing | D35: =Regions!C7*Assumptions!$C$13 -> 40 | E35: interviews | F35: =Assumptions!$C$28 -> 0.15 | G35: =D35*F35 -> 6 | H35: =G35*Assumptions!$C$5 -> 1662
A36: 2 | B36: Data and coding | C36: Multan: data entry and coding | D36: =Regions!C7*Assumptions!$C$18 -> 4 | E36: days | F36: =Assumptions!$C$7 -> 15 | G36: =D36*F36 -> 60 | H36: =G36*Assumptions!$C$5 -> 16620 | I36: Function module entry and double check.
A37: 2 | B37: Fieldwork teams and travel | C37: Uch Sharif and Bahawalpur: enumerator days | D37: =Regions!K8 -> 14 | E37: enumerator days | F37: =Assumptions!$C$7 -> 15 | G37: =D37*F37 -> 210 | H37: =G37*Assumptions!$C$5 -> 58170 | I37: Two enumerators per visit outside Lahore; singly in Lahore, as in the Mittal budget.
A38: 2 | B38: Fieldwork teams and travel | C38: Uch Sharif and Bahawalpur: female enumerator days | D38: =Regions!L8 -> 4 | E38: days | F38: =Assumptions!$C$9 -> 15 | G38: =D38*F38 -> 60 | H38: =G38*Assumptions!$C$5 -> 16620 | I38: Women's spaces and women devotee interviews.
A39: 2 | B39: Fieldwork teams and travel | C39: Uch Sharif and Bahawalpur: field coordinator days | D39: =Regions!M8 -> 7 | E39: days | F39: =Assumptions!$C$8 -> 25 | G39: =D39*F39 -> 175 | H39: =G39*Assumptions!$C$5 -> 48475 | I39: Supervision of outstation teams.
A40: 2 | B40: Fieldwork teams and travel | C40: Uch Sharif and Bahawalpur: local transport | D40: =Regions!J8 -> 7 | E40: team field days | F40: =Assumptions!$C$22 -> 8 | G40: =D40*F40 -> 56 | H40: =G40*Assumptions!$C$5 -> 15512 | I40: Ride hail and rickshaw between sites.
A41: 2 | B41: Fieldwork teams and travel | C41: Uch Sharif and Bahawalpur: intercity fares | D41: =Regions!D8 -> 3 | E41: travellers | F41: =Regions!E8/Assumptions!$C$5 -> 22.238267 | G41: =D41*F41 -> 66.714801 | H41: =G41*Assumptions!$C$5 -> 18480 | I41: Round trip bus fare per traveller; see Regions.
A42: 2 | B42: Fieldwork teams and travel | C42: Uch Sharif and Bahawalpur: lodging | D42: =ROUNDUP(Regions!D8/Assumptions!$C$20,0)*Regions!N8 -> 16 | E42: room nights | F42: =Assumptions!$C$19 -> 35 | G42: =D42*F42 -> 560 | H42: =G42*Assumptions!$C$5 -> 155120 | I42: Budget hotel, twin share.
A43: 2 | B43: Fieldwork teams and travel | C43: Uch Sharif and Bahawalpur: meals away from home | D43: =Regions!D8*Regions!N8 -> 24 | E43: traveller days | F43: =Assumptions!$C$21 -> 10 | G43: =D43*F43 -> 240 | H43: =G43*Assumptions!$C$5 -> 66480 | I43: Per traveller per night away.
A44: 2 | B44: Interviews | C44: Uch Sharif and Bahawalpur: transcription and translation | D44: =Regions!C8*Assumptions!$C$13*Assumptions!$C$15/60 -> 16.666667 | E44: audio hours | F44: =Assumptions!$C$17 -> 12 | G44: =D44*F44 -> 200 | H44: =G44*Assumptions!$C$5 -> 55400 | I44: Five interviews per shrine.
A45: 2 | B45: Interviews | C45: Uch Sharif and Bahawalpur: tokens of thanks to devotees | D45: =Regions!C8*Assumptions!$C$14 -> 24 | E45: interviews | F45: =Assumptions!$C$16/Assumptions!$C$5 -> 1.8050542 | G45: =D45*F45 -> 43.3213 | H45: =G45*Assumptions!$C$5 -> 12000 | I45: Subject to CUHS and Rauf's decision.
A46: 2 | B46: Interviews | C46: Uch Sharif and Bahawalpur: consent forms and printing | D46: =Regions!C8*Assumptions!$C$13 -> 40 | E46: interviews | F46: =Assumptions!$C$28 -> 0.15 | G46: =D46*F46 -> 6 | H46: =G46*Assumptions!$C$5 -> 1662
A47: 2 | B47: Data and coding | C47: Uch Sharif and Bahawalpur: data entry and coding | D47: =Regions!C8*Assumptions!$C$18 -> 4 | E47: days | F47: =Assumptions!$C$7 -> 15 | G47: =D47*F47 -> 60 | H47: =G47*Assumptions!$C$5 -> 16620 | I47: Function module entry and double check.
A48: 2 | B48: Fieldwork teams and travel | C48: Jhang: enumerator days | D48: =Regions!K9 -> 8 | E48: enumerator days | F48: =Assumptions!$C$7 -> 15 | G48: =D48*F48 -> 120 | H48: =G48*Assumptions!$C$5 -> 33240 | I48: Two enumerators per visit outside Lahore; singly in Lahore, as in the Mittal budget.
A49: 2 | B49: Fieldwork teams and travel | C49: Jhang: female enumerator days | D49: =Regions!L9 -> 2 | E49: days | F49: =Assumptions!$C$9 -> 15 | G49: =D49*F49 -> 30 | H49: =G49*Assumptions!$C$5 -> 8310 | I49: Women's spaces and women devotee interviews.
A50: 2 | B50: Fieldwork teams and travel | C50: Jhang: field coordinator days | D50: =Regions!M9 -> 4 | E50: days | F50: =Assumptions!$C$8 -> 25 | G50: =D50*F50 -> 100 | H50: =G50*Assumptions!$C$5 -> 27700 | I50: Supervision of outstation teams.
A51: 2 | B51: Fieldwork teams and travel | C51: Jhang: local transport | D51: =Regions!J9 -> 4 | E51: team field days | F51: =Assumptions!$C$22 -> 8 | G51: =D51*F51 -> 32 | H51: =G51*Assumptions!$C$5 -> 8864 | I51: Ride hail and rickshaw between sites.
A52: 2 | B52: Fieldwork teams and travel | C52: Jhang: intercity fares | D52: =Regions!D9 -> 3 | E52: travellers | F52: =Regions!E9/Assumptions!$C$5 -> 11.407942 | G52: =D52*F52 -> 34.223827 | H52: =G52*Assumptions!$C$5 -> 9480 | I52: Round trip bus fare per traveller; see Regions.
A53: 2 | B53: Fieldwork teams and travel | C53: Jhang: lodging | D53: =ROUNDUP(Regions!D9/Assumptions!$C$20,0)*Regions!N9 -> 10 | E53: room nights | F53: =Assumptions!$C$19 -> 35 | G53: =D53*F53 -> 350 | H53: =G53*Assumptions!$C$5 -> 96950 | I53: Budget hotel, twin share.
A54: 2 | B54: Fieldwork teams and travel | C54: Jhang: meals away from home | D54: =Regions!D9*Regions!N9 -> 15 | E54: traveller days | F54: =Assumptions!$C$21 -> 10 | G54: =D54*F54 -> 150 | H54: =G54*Assumptions!$C$5 -> 41550 | I54: Per traveller per night away.
A55: 2 | B55: Interviews | C55: Jhang: transcription and translation | D55: =Regions!C9*Assumptions!$C$13*Assumptions!$C$15/60 -> 8.3333333 | E55: audio hours | F55: =Assumptions!$C$17 -> 12 | G55: =D55*F55 -> 100 | H55: =G55*Assumptions!$C$5 -> 27700 | I55: Five interviews per shrine.
A56: 2 | B56: Interviews | C56: Jhang: tokens of thanks to devotees | D56: =Regions!C9*Assumptions!$C$14 -> 12 | E56: interviews | F56: =Assumptions!$C$16/Assumptions!$C$5 -> 1.8050542 | G56: =D56*F56 -> 21.66065 | H56: =G56*Assumptions!$C$5 -> 6000 | I56: Subject to CUHS and Rauf's decision.
A57: 2 | B57: Interviews | C57: Jhang: consent forms and printing | D57: =Regions!C9*Assumptions!$C$13 -> 20 | E57: interviews | F57: =Assumptions!$C$28 -> 0.15 | G57: =D57*F57 -> 3 | H57: =G57*Assumptions!$C$5 -> 831
A58: 2 | B58: Data and coding | C58: Jhang: data entry and coding | D58: =Regions!C9*Assumptions!$C$18 -> 2 | E58: days | F58: =Assumptions!$C$7 -> 15 | G58: =D58*F58 -> 30 | H58: =G58*Assumptions!$C$5 -> 8310 | I58: Function module entry and double check.
A59: 2 | B59: Fieldwork teams and travel | C59: Okara: enumerator days | D59: =Regions!K10 -> 8 | E59: enumerator days | F59: =Assumptions!$C$7 -> 15 | G59: =D59*F59 -> 120 | H59: =G59*Assumptions!$C$5 -> 33240 | I59: Two enumerators per visit outside Lahore; singly in Lahore, as in the Mittal budget.
A60: 2 | B60: Fieldwork teams and travel | C60: Okara: female enumerator days | D60: =Regions!L10 -> 2 | E60: days | F60: =Assumptions!$C$9 -> 15 | G60: =D60*F60 -> 30 | H60: =G60*Assumptions!$C$5 -> 8310 | I60: Women's spaces and women devotee interviews.
A61: 2 | B61: Fieldwork teams and travel | C61: Okara: field coordinator days | D61: =Regions!M10 -> 4 | E61: days | F61: =Assumptions!$C$8 -> 25 | G61: =D61*F61 -> 100 | H61: =G61*Assumptions!$C$5 -> 27700 | I61: Supervision of outstation teams.
A62: 2 | B62: Fieldwork teams and travel | C62: Okara: local transport | D62: =Regions!J10 -> 4 | E62: team field days | F62: =Assumptions!$C$22 -> 8 | G62: =D62*F62 -> 32 | H62: =G62*Assumptions!$C$5 -> 8864 | I62: Ride hail and rickshaw between sites.
A63: 2 | B63: Fieldwork teams and travel | C63: Okara: intercity fares | D63: =Regions!D10 -> 3 | E63: travellers | F63: =Regions!E10/Assumptions!$C$5 -> 6.4259928 | G63: =D63*F63 -> 19.277978 | H63: =G63*Assumptions!$C$5 -> 5340 | I63: Round trip bus fare per traveller; see Regions.
A64: 2 | B64: Fieldwork teams and travel | C64: Okara: lodging | D64: =ROUNDUP(Regions!D10/Assumptions!$C$20,0)*Regions!N10 -> 10 | E64: room nights | F64: =Assumptions!$C$19 -> 35 | G64: =D64*F64 -> 350 | H64: =G64*Assumptions!$C$5 -> 96950 | I64: Budget hotel, twin share.
A65: 2 | B65: Fieldwork teams and travel | C65: Okara: meals away from home | D65: =Regions!D10*Regions!N10 -> 15 | E65: traveller days | F65: =Assumptions!$C$21 -> 10 | G65: =D65*F65 -> 150 | H65: =G65*Assumptions!$C$5 -> 41550 | I65: Per traveller per night away.
A66: 2 | B66: Interviews | C66: Okara: transcription and translation | D66: =Regions!C10*Assumptions!$C$13*Assumptions!$C$15/60 -> 8.3333333 | E66: audio hours | F66: =Assumptions!$C$17 -> 12 | G66: =D66*F66 -> 100 | H66: =G66*Assumptions!$C$5 -> 27700 | I66: Five interviews per shrine.
A67: 2 | B67: Interviews | C67: Okara: tokens of thanks to devotees | D67: =Regions!C10*Assumptions!$C$14 -> 12 | E67: interviews | F67: =Assumptions!$C$16/Assumptions!$C$5 -> 1.8050542 | G67: =D67*F67 -> 21.66065 | H67: =G67*Assumptions!$C$5 -> 6000 | I67: Subject to CUHS and Rauf's decision.
A68: 2 | B68: Interviews | C68: Okara: consent forms and printing | D68: =Regions!C10*Assumptions!$C$13 -> 20 | E68: interviews | F68: =Assumptions!$C$28 -> 0.15 | G68: =D68*F68 -> 3 | H68: =G68*Assumptions!$C$5 -> 831
A69: 2 | B69: Data and coding | C69: Okara: data entry and coding | D69: =Regions!C10*Assumptions!$C$18 -> 2 | E69: days | F69: =Assumptions!$C$7 -> 15 | G69: =D69*F69 -> 30 | H69: =G69*Assumptions!$C$5 -> 8310 | I69: Function module entry and double check.
A70: 2 | B70: Fieldwork teams and travel | C70: Kasur: enumerator days | D70: =Regions!K11 -> 8 | E70: enumerator days | F70: =Assumptions!$C$7 -> 15 | G70: =D70*F70 -> 120 | H70: =G70*Assumptions!$C$5 -> 33240 | I70: Two enumerators per visit outside Lahore; singly in Lahore, as in the Mittal budget.
A71: 2 | B71: Fieldwork teams and travel | C71: Kasur: female enumerator days | D71: =Regions!L11 -> 2 | E71: days | F71: =Assumptions!$C$9 -> 15 | G71: =D71*F71 -> 30 | H71: =G71*Assumptions!$C$5 -> 8310 | I71: Women's spaces and women devotee interviews.
A72: 2 | B72: Fieldwork teams and travel | C72: Kasur: field coordinator days | D72: =Regions!M11 -> 4 | E72: days | F72: =Assumptions!$C$8 -> 25 | G72: =D72*F72 -> 100 | H72: =G72*Assumptions!$C$5 -> 27700 | I72: Supervision of outstation teams.
A73: 2 | B73: Fieldwork teams and travel | C73: Kasur: local transport | D73: =Regions!J11 -> 4 | E73: team field days | F73: =Assumptions!$C$22 -> 8 | G73: =D73*F73 -> 32 | H73: =G73*Assumptions!$C$5 -> 8864 | I73: Ride hail and rickshaw between sites.
A74: 2 | B74: Fieldwork teams and travel | C74: Kasur: intercity fares | D74: =Regions!D11 -> 2 | E74: travellers | F74: =Regions!E11/Assumptions!$C$5 -> 4.33213 | G74: =D74*F74 -> 8.6642599 | H74: =G74*Assumptions!$C$5 -> 2400 | I74: Round trip bus fare per traveller; see Regions.
A75: 2 | B75: Fieldwork teams and travel | C75: Kasur: lodging | D75: =ROUNDUP(Regions!D11/Assumptions!$C$20,0)*Regions!N11 -> 0 | E75: room nights | F75: =Assumptions!$C$19 -> 35 | G75: =D75*F75 -> 0 | H75: =G75*Assumptions!$C$5 -> 0 | I75: Budget hotel, twin share.
A76: 2 | B76: Fieldwork teams and travel | C76: Kasur: meals away from home | D76: =Regions!D11*Regions!N11 -> 0 | E76: traveller days | F76: =Assumptions!$C$21 -> 10 | G76: =D76*F76 -> 0 | H76: =G76*Assumptions!$C$5 -> 0 | I76: Per traveller per night away.
A77: 2 | B77: Interviews | C77: Kasur: transcription and translation | D77: =Regions!C11*Assumptions!$C$13*Assumptions!$C$15/60 -> 8.3333333 | E77: audio hours | F77: =Assumptions!$C$17 -> 12 | G77: =D77*F77 -> 100 | H77: =G77*Assumptions!$C$5 -> 27700 | I77: Five interviews per shrine.
A78: 2 | B78: Interviews | C78: Kasur: tokens of thanks to devotees | D78: =Regions!C11*Assumptions!$C$14 -> 12 | E78: interviews | F78: =Assumptions!$C$16/Assumptions!$C$5 -> 1.8050542 | G78: =D78*F78 -> 21.66065 | H78: =G78*Assumptions!$C$5 -> 6000 | I78: Subject to CUHS and Rauf's decision.
A79: 2 | B79: Interviews | C79: Kasur: consent forms and printing | D79: =Regions!C11*Assumptions!$C$13 -> 20 | E79: interviews | F79: =Assumptions!$C$28 -> 0.15 | G79: =D79*F79 -> 3 | H79: =G79*Assumptions!$C$5 -> 831
A80: 2 | B80: Data and coding | C80: Kasur: data entry and coding | D80: =Regions!C11*Assumptions!$C$18 -> 2 | E80: days | F80: =Assumptions!$C$7 -> 15 | G80: =D80*F80 -> 30 | H80: =G80*Assumptions!$C$5 -> 8310 | I80: Function module entry and double check.
A81: 2 | B81: Fieldwork teams and travel | C81: Taunsa and Dera Ghazi Khan: enumerator days | D81: =Regions!K12 -> 8 | E81: enumerator days | F81: =Assumptions!$C$7 -> 15 | G81: =D81*F81 -> 120 | H81: =G81*Assumptions!$C$5 -> 33240 | I81: Two enumerators per visit outside Lahore; singly in Lahore, as in the Mittal budget.
A82: 2 | B82: Fieldwork teams and travel | C82: Taunsa and Dera Ghazi Khan: female enumerator days | D82: =Regions!L12 -> 2 | E82: days | F82: =Assumptions!$C$9 -> 15 | G82: =D82*F82 -> 30 | H82: =G82*Assumptions!$C$5 -> 8310 | I82: Women's spaces and women devotee interviews.
A83: 2 | B83: Fieldwork teams and travel | C83: Taunsa and Dera Ghazi Khan: field coordinator days | D83: =Regions!M12 -> 4 | E83: days | F83: =Assumptions!$C$8 -> 25 | G83: =D83*F83 -> 100 | H83: =G83*Assumptions!$C$5 -> 27700 | I83: Supervision of outstation teams.
A84: 2 | B84: Fieldwork teams and travel | C84: Taunsa and Dera Ghazi Khan: local transport | D84: =Regions!J12 -> 4 | E84: team field days | F84: =Assumptions!$C$22 -> 8 | G84: =D84*F84 -> 32 | H84: =G84*Assumptions!$C$5 -> 8864 | I84: Ride hail and rickshaw between sites.
A85: 2 | B85: Fieldwork teams and travel | C85: Taunsa and Dera Ghazi Khan: intercity fares | D85: =Regions!D12 -> 3 | E85: travellers | F85: =Regions!E12/Assumptions!$C$5 -> 28.880866 | G85: =D85*F85 -> 86.642599 | H85: =G85*Assumptions!$C$5 -> 24000 | I85: Round trip bus fare per traveller; see Regions.
A86: 2 | B86: Fieldwork teams and travel | C86: Taunsa and Dera Ghazi Khan: lodging | D86: =ROUNDUP(Regions!D12/Assumptions!$C$20,0)*Regions!N12 -> 10 | E86: room nights | F86: =Assumptions!$C$19 -> 35 | G86: =D86*F86 -> 350 | H86: =G86*Assumptions!$C$5 -> 96950 | I86: Budget hotel, twin share.
A87: 2 | B87: Fieldwork teams and travel | C87: Taunsa and Dera Ghazi Khan: meals away from home | D87: =Regions!D12*Regions!N12 -> 15 | E87: traveller days | F87: =Assumptions!$C$21 -> 10 | G87: =D87*F87 -> 150 | H87: =G87*Assumptions!$C$5 -> 41550 | I87: Per traveller per night away.
A88: 2 | B88: Interviews | C88: Taunsa and Dera Ghazi Khan: transcription and translation | D88: =Regions!C12*Assumptions!$C$13*Assumptions!$C$15/60 -> 8.3333333 | E88: audio hours | F88: =Assumptions!$C$17 -> 12 | G88: =D88*F88 -> 100 | H88: =G88*Assumptions!$C$5 -> 27700 | I88: Five interviews per shrine.
A89: 2 | B89: Interviews | C89: Taunsa and Dera Ghazi Khan: tokens of thanks to devotees | D89: =Regions!C12*Assumptions!$C$14 -> 12 | E89: interviews | F89: =Assumptions!$C$16/Assumptions!$C$5 -> 1.8050542 | G89: =D89*F89 -> 21.66065 | H89: =G89*Assumptions!$C$5 -> 6000 | I89: Subject to CUHS and Rauf's decision.
A90: 2 | B90: Interviews | C90: Taunsa and Dera Ghazi Khan: consent forms and printing | D90: =Regions!C12*Assumptions!$C$13 -> 20 | E90: interviews | F90: =Assumptions!$C$28 -> 0.15 | G90: =D90*F90 -> 3 | H90: =G90*Assumptions!$C$5 -> 831
A91: 2 | B91: Data and coding | C91: Taunsa and Dera Ghazi Khan: data entry and coding | D91: =Regions!C12*Assumptions!$C$18 -> 2 | E91: days | F91: =Assumptions!$C$7 -> 15 | G91: =D91*F91 -> 30 | H91: =G91*Assumptions!$C$5 -> 8310 | I91: Function module entry and double check.
A92: 3 | B92: Fieldwork teams and travel | C92: Sindh: Karachi and Thatta: enumerator days | D92: =Regions!K13 -> 10 | E92: enumerator days | F92: =Assumptions!$C$7 -> 15 | G92: =D92*F92 -> 150 | H92: =G92*Assumptions!$C$5 -> 41550 | I92: Two enumerators per visit outside Lahore; singly in Lahore, as in the Mittal budget.
A93: 3 | B93: Fieldwork teams and travel | C93: Sindh: Karachi and Thatta: female enumerator days | D93: =Regions!L13 -> 3 | E93: days | F93: =Assumptions!$C$9 -> 15 | G93: =D93*F93 -> 45 | H93: =G93*Assumptions!$C$5 -> 12465 | I93: Women's spaces and women devotee interviews.
A94: 3 | B94: Fieldwork teams and travel | C94: Sindh: Karachi and Thatta: field coordinator days | D94: =Regions!M13 -> 5 | E94: days | F94: =Assumptions!$C$8 -> 25 | G94: =D94*F94 -> 125 | H94: =G94*Assumptions!$C$5 -> 34625 | I94: Supervision of outstation teams.
A95: 3 | B95: Fieldwork teams and travel | C95: Sindh: Karachi and Thatta: local transport | D95: =Regions!J13 -> 5 | E95: team field days | F95: =Assumptions!$C$22 -> 8 | G95: =D95*F95 -> 40 | H95: =G95*Assumptions!$C$5 -> 11080 | I95: Ride hail and rickshaw between sites.
A96: 3 | B96: Fieldwork teams and travel | C96: Sindh: Karachi and Thatta: domestic flights | D96: =Regions!D13*Regions!F13 -> 2 | E96: one way legs | F96: =Assumptions!$C$24 -> 90 | G96: =D96*F96 -> 180 | H96: =G96*Assumptions!$C$5 -> 49860 | I96: Lahore to Karachi and back.
A97: 3 | B97: Fieldwork teams and travel | C97: Sindh: Karachi and Thatta: hired car with driver | D97: =Regions!G13 -> 4 | E97: days | F97: =Assumptions!$C$23 -> 60 | G97: =D97*F97 -> 240 | H97: =G97*Assumptions!$C$5 -> 66480 | I97: Distances between Sindh shrines.
A98: 3 | B98: Fieldwork teams and travel | C98: Sindh: Karachi and Thatta: lodging | D98: =ROUNDUP(Regions!D13/Assumptions!$C$20,0)*Regions!N13 -> 6 | E98: room nights | F98: =Assumptions!$C$19 -> 35 | G98: =D98*F98 -> 210 | H98: =G98*Assumptions!$C$5 -> 58170 | I98: Budget hotel, twin share.
A99: 3 | B99: Fieldwork teams and travel | C99: Sindh: Karachi and Thatta: meals away from home | D99: =Regions!D13*Regions!N13 -> 6 | E99: traveller days | F99: =Assumptions!$C$21 -> 10 | G99: =D99*F99 -> 60 | H99: =G99*Assumptions!$C$5 -> 16620 | I99: Per traveller per night away.
A100: 3 | B100: Interviews | C100: Sindh: Karachi and Thatta: transcription and translation | D100: =Regions!C13*Assumptions!$C$13*Assumptions!$C$15/60 -> 12.5 | E100: audio hours | F100: =Assumptions!$C$17 -> 12 | G100: =D100*F100 -> 150 | H100: =G100*Assumptions!$C$5 -> 41550 | I100: Five interviews per shrine.
A101: 3 | B101: Interviews | C101: Sindh: Karachi and Thatta: tokens of thanks to devotees | D101: =Regions!C13*Assumptions!$C$14 -> 18 | E101: interviews | F101: =Assumptions!$C$16/Assumptions!$C$5 -> 1.8050542 | G101: =D101*F101 -> 32.490975 | H101: =G101*Assumptions!$C$5 -> 9000 | I101: Subject to CUHS and Rauf's decision.
...

Sheet Sources
A1: Sources consulted, 13 October 2026
A3: Figure | B3: Source | C3: URL
A4: PKR 277.11 per USD, 30 Sep 2026 | B4: ProPakistani | C4: https://propakistani.pk/2026/09/30/pkr-breaks-another-record-against-dollar/
A5: Punjab minimum wage PKR 40,000 a month from 1 Jul 2025 | B5: WageIndicator | C5: https://wageindicator.org/salary/minimum-wage/pakistan/168-punjab
A6: Daewoo Express fares from Lahore and Multan | B6: PK Buses fare list | C6: https://pkbuses.com/daewoo-express-ticket-price
A7: Lahore to Multan bus fares by operator | B7: Bookme | C7: https://bookme.pk/lahore-to-multan-bus-ticket-price
A8: Lahore to Karachi flights from PKR 17,240 | B8: Air Arabia | C8: https://flights.airarabia.com/en-pk/flights-from-lahore-to-karachi
A9: Multan hotel prices | B9: Champion Traveler | C9: https://championtraveler.com/price/cost-of-a-trip-to-multan-pk
A10: CZUR ET18 Pro at PKR 181,000 | B10: Paklap | C10: https://www.paklap.pk/czur-et18-scanner-price-reviews-pakistan.html
A11: Zoom H5studio at $349.99 | B11: Trew Audio | C11: https://www.trewaudio.com/product/zoom-h5studio-handy-recorder/
A12: Urdu transcription from $1.02 a minute | B12: GoTranscript | C12: https://gotranscript.com/transcribe-urdu-audio-to-english
A13: Enumerator, airfare, transport and archive rates | B13: Rauf Nawaz, Mittal Statement of Rationale and Budget | C13: Mittal Proposal folder, Google Drive
